pyvlib/__init__.py
pyvlib/fileio.py
pyvlib/filesys.py
pyvlib/version.py
pyvlib/cg/__init__.py
pyvlib/cg/bbox.py
pyvlib/cg/io.py
pyvlib/cv/__init__.py
pyvlib/cv/crop.py
pyvlib/cv/draw.py
pyvlib/cv/gif.py
pyvlib/cv/io.py
pyvlib/cv/mask.py
pyvlib/cv/reshape.py
pyvlib/cv/video.py
pyvlib-0.0.1.dist-info/METADATA
pyvlib-0.0.1.dist-info/RECORD
pyvlib-0.0.1.dist-info/WHEEL
pyvlib-0.0.1.dist-info/top_level.txt
