Metadata-Version: 2.1
Name: pyvlib
Version: 0.0.1
Summary: Python vlib
Home-page: https://github.com/VVingerfly/pyvlib
Author: Li Wei
Author-email: wei587me@163.com
License: UNKNOWN
Platform: UNKNOWN
Classifier: Programming Language :: Python :: 3
Classifier: Operating System :: OS Independent
Requires-Python: >=3.6.0
Provides-Extra: matplotlib
Provides-Extra: pyrender
Provides-Extra: open3d
Provides-Extra: all
Provides-Extra: all
Requires-Dist: pyrender (>=0.1.23); extra == 'all'
Requires-Dist: trimesh (>=2.37.6); extra == 'all'
Requires-Dist: shapely; extra == 'all'
Requires-Dist: matplotlib; extra == 'all'
Requires-Dist: open3d-python; extra == 'all'
Provides-Extra: matplotlib
Requires-Dist: matplotlib; extra == 'matplotlib'
Provides-Extra: open3d
Requires-Dist: open3d-python; extra == 'open3d'
Provides-Extra: pyrender
Requires-Dist: pyrender (>=0.1.23); extra == 'pyrender'
Requires-Dist: trimesh (>=2.37.6); extra == 'pyrender'
Requires-Dist: shapely; extra == 'pyrender'
